setup.py
ustciscr/__init__.py
ustciscr/get_score.py
ustciscr.egg-info/PKG-INFO
ustciscr.egg-info/SOURCES.txt
ustciscr.egg-info/dependency_links.txt
ustciscr.egg-info/requires.txt
ustciscr.egg-info/top_level.txt