Metadata-Version: 1.0
Name: ustciscr
Version: 2.2.3
Summary: This is ustc-iscr score package
Home-page: https://github.com/WolverineQin/ustciscr
Author: qjqqjq
Author-email: 1102692995@qq.com
License: MIT Licence
Keywords: pip,ustciscr,featureextraction
Platform: any
